hvm/__init__.py
hvm/_hooks.py
hvm/env.py
hvm/error.py
hvm/toolchain.py
hvm/tutorial.py
hvm/typing.py
hvm/utils.py
hvm/_ffi/__init__.py
hvm/_ffi/_pyversion.py
hvm/_ffi/_selector.py
hvm/_ffi/base.py
hvm/_ffi/error.py
hvm/_ffi/libinfo.py
hvm/_ffi/registry.py
hvm/_ffi/runtime_ctypes.py
hvm/_ffi/_c_ext/__init__.py
hvm/_ffi/_c_ext/_loader.py
hvm/_ffi/_c_ext/fast_c_api.cc
hvm/_ffi/_c_ext/hvm_script_api.so
hvm/_ffi/_c_ext/object.py
hvm/_ffi/_c_ext/packed_func.py
hvm/_ffi/_c_ext/types.py
hvm/cfg/__init__.py
hvm/cfg/builder.py
hvm/cfg/model.py
hvm/contrib/__init__.py
hvm/contrib/_filelock.py
hvm/contrib/cc.py
hvm/contrib/cpp_extension.py
hvm/contrib/inspect3_9_1_patch.py
hvm/contrib/ndk.py
hvm/contrib/statistic.py
hvm/contrib/tar.py
hvm/contrib/util.py
hvm/extension/__init__.py
hvm/extension/cpp/pytorch/CMakeLists.txt
hvm/extension/cpp/pytorch/src/matx_inc.h
hvm/extension/cpp/pytorch/src/tensor_api.cc
hvm/extension/cpp/pytorch/src/torch_inc.h
hvm/extension/cpp/pytorch/src/torch_infer_op.cc
hvm/extension/cpp/pytorch/src/torch_infer_op.h
hvm/extension/cpp/pytorch/src/torch_model.cc
hvm/extension/cpp/pytorch/src/torch_model.h
hvm/extension/cpp/tensorflow/CMakeLists.txt
hvm/extension/cpp/tensorflow/src/_tensorflow_cc_savedmodel_constants.h
hvm/extension/cpp/tensorflow/src/_tensorflow_cc_savedmodel_reader.h
hvm/extension/cpp/tensorflow/src/_tensorflow_cc_savedmodel_signature_constants.h
hvm/extension/cpp/tensorflow/src/_tensorflow_cc_savedmodel_tag_constants.h
hvm/extension/cpp/tensorflow/src/tf_dataset_callback_op.cc
hvm/extension/cpp/tensorflow/src/tf_dataset_callback_op.h
hvm/extension/cpp/tensorflow/src/tf_infer_op.cc
hvm/extension/cpp/tensorflow/src/tf_infer_op.h
hvm/extension/cpp/tensorflow/src/tf_model.cc
hvm/extension/cpp/tensorflow/src/tf_model.h
hvm/extension/cpp/tensorflow/src/tf_utils.cc
hvm/extension/cpp/tensorflow/src/tf_utils.h
hvm/extension/cpp/tvm/CMakeLists.txt
hvm/extension/cpp/tvm/src/tvm_infer_op.cc
hvm/extension/cpp/tvm/src/tvm_infer_op.h
hvm-0.6.1.dist-info/METADATA
hvm-0.6.1.dist-info/WHEEL
hvm-0.6.1.dist-info/top_level.txt
hvm-0.6.1.dist-info/RECORD
